imfusion/__init__.py
imfusion/compat.py
imfusion/ctg.py
imfusion/merge.py
imfusion/model.py
imfusion/build/__init__.py
imfusion/build/util.py
imfusion/build/indexers/__init__.py
imfusion/build/indexers/base.py
imfusion/build/indexers/star.py
imfusion/build/indexers/tophat.py
imfusion/expression/__init__.py
imfusion/expression/counts.py
imfusion/expression/stats.py
imfusion/expression/test.py
imfusion/external/__init__.py
imfusion/external/bowtie.py
imfusion/external/compound.py
imfusion/external/feature_counts.py
imfusion/external/sambamba.py
imfusion/external/star.py
imfusion/external/star_fusion.py
imfusion/external/stringtie.py
imfusion/external/tophat.py
imfusion/external/util.py
imfusion/insertions/__init__.py
imfusion/insertions/util.py
imfusion/insertions/aligners/__init__.py
imfusion/insertions/aligners/base.py
imfusion/insertions/aligners/star.py
imfusion/insertions/aligners/tophat.py
imfusion/main/__init__.py
imfusion/main/build.py
imfusion/main/ctg.py
imfusion/main/dispatch.py
imfusion/main/expression.py
imfusion/main/insertions.py
imfusion/main/merge.py
imfusion/util/__init__.py
imfusion/util/frozendict.py
imfusion/util/genomic.py
imfusion/util/path.py
imfusion/util/tabix.py
imfusion-0.3.2.dist-info/DESCRIPTION.rst
imfusion-0.3.2.dist-info/METADATA
imfusion-0.3.2.dist-info/RECORD
imfusion-0.3.2.dist-info/WHEEL
imfusion-0.3.2.dist-info/entry_points.txt
imfusion-0.3.2.dist-info/metadata.json
imfusion-0.3.2.dist-info/top_level.txt
