Metadata-Version: 2.0
Name: imfusion
Version: 0.3.2
Summary: Tool for identifying transposon insertions in Insertional Mutagenesis screens from gene-transposon fusions using single- and paired-end RNA-sequencing data.
Home-page: https://github.com/nki-ccb/imfusion
Author: Julian de Ruiter
Author-email: julianderuiter@gmail.com
License: MIT license
Platform: UNKNOWN
Requires-Dist: future
Requires-Dist: htseq (>=0.7.2)
Requires-Dist: intervaltree
Requires-Dist: matplotlib
Requires-Dist: numexpr
Requires-Dist: pandas (>=0.19.0)
Requires-Dist: pathlib2
Requires-Dist: pyfaidx
Requires-Dist: pysam (>=0.9.1)
Requires-Dist: scipy
Requires-Dist: seaborn
Requires-Dist: toolz
Requires-Dist: typing
Provides-Extra: de_single
Requires-Dist: rpy2; extra == 'de_single'
Provides-Extra: dev
Requires-Dist: bumpversion; extra == 'dev'
Requires-Dist: pytest (>=2.7); extra == 'dev'
Requires-Dist: pytest-cov; extra == 'dev'
Requires-Dist: pytest-helpers-namespace; extra == 'dev'
Requires-Dist: pytest-mock; extra == 'dev'
Requires-Dist: python-coveralls; extra == 'dev'
Requires-Dist: seaborn; extra == 'dev'
Requires-Dist: sphinx; extra == 'dev'
Requires-Dist: sphinx-autobuild; extra == 'dev'
Requires-Dist: sphinx-rtd-theme; extra == 'dev'
